vfd/__init__.py
vfd/builder.py
vfd/cli.py
vfd/gui.py
vfd/vfd.py
vfd/img/README.md
vfd/img/document-open.png
vfd/img/document-save-as.png
vfd/img/document-save.png
vfd/img/go-jump.png
vfd/img/image-x-generic.png
vfd/img/python.png
vfd/img/system-log-out.png
vfd/img/vfdlogo.ico
vfd/img/vfdlogo.png
vfd/img/x-office-spreadsheet.png
vfd-0.3.2.dist-info/METADATA
vfd-0.3.2.dist-info/RECORD
vfd-0.3.2.dist-info/WHEEL
vfd-0.3.2.dist-info/entry_points.txt
vfd-0.3.2.dist-info/top_level.txt
