Metadata-Version: 2.1
Name: vfd
Version: 0.3.2
Summary: Vernacular Figure Description
Home-page: https://github.com/Dih5/vfd
Author: Dih5
Author-email: dihedralfive@gmail.com
License: LGPLv3+
Keywords: vfd,plotting
Platform: UNKNOWN
Classifier: Development Status :: 3 - Alpha
Classifier: Intended Audience :: Science/Research
Classifier: License :: OSI Approved :: GNU Lesser General Public License v3 or later (LGPLv3+)
Classifier: Natural Language :: English
Classifier: Programming Language :: Python :: 2
Classifier: Programming Language :: Python :: 2.7
Classifier: Programming Language :: Python :: 3
Classifier: Programming Language :: Python :: 3.4
Classifier: Programming Language :: Python :: 3.5
Classifier: Programming Language :: Python :: 3.6
Requires-Dist: Click (>=6.0)
Requires-Dist: jsonschema
Requires-Dist: matplotlib
Requires-Dist: xlsxwriter
Requires-Dist: pillow
